leap.mx-0.5.0_2_gea64e46-nspkg.pth
usr/local/bin/mx.tac
leap.mx-0.5.0_2_gea64e46.dist-info/top_level.txt
leap.mx-0.5.0_2_gea64e46.dist-info/DESCRIPTION.rst
leap.mx-0.5.0_2_gea64e46.dist-info/pydist.json
leap.mx-0.5.0_2_gea64e46.dist-info/METADATA
leap.mx-0.5.0_2_gea64e46.dist-info/namespace_packages.txt
leap.mx-0.5.0_2_gea64e46.dist-info/WHEEL
leap.mx-0.5.0_2_gea64e46.dist-info/RECORD
leap/mx/mail_receiver.py
leap/mx/couchdbhelper.py
leap/mx/__init__.py
leap/mx/alias_resolver.py
leap/mx/_version.py
leap/mx/check_recipient_access.py
leap/mx/tester.py
leap/mx/tests/__init__.py
etc/init.d/leap_mx
