Metadata-Version: 2.0
Name: leap.mx
Version: 0.5.0-2-gea64e46
Summary: An asynchronous, transparently-encrypting remailer for the LEAP platform
Home-page: http://github.com/leapcode/leap_mx
Author: Kali Kaneko
Author-email: kali@leap.se
License: AGPLv3+
Download-URL: https://github.com/leapcode/leap_mx/archive/0.5.0.tar.gz
Platform: UNKNOWN
Classifier: Development Status :: 3 - Alpha
Classifier: Environment :: No Input/Output (Daemon)
Classifier: Framework :: Twisted
Classifier: Intended Audience :: Developers
Classifier: License :: OSI Approved :: GNU Affero General Public License v3 or later (AGPLv3+)
Classifier: Natural Language :: English
Classifier: Operating System :: POSIX :: Linux
Classifier: Programming Language :: Python :: 2.6
Classifier: Programming Language :: Python :: 2.7
Classifier: Topic :: Communications :: Email
Classifier: Topic :: Security :: Cryptography
Requires-Dist: Twisted (>=12.0.2)
Requires-Dist: paisley (>=0.3.1)
Requires-Dist: couchdb
Requires-Dist: leap.common (>=0.3.5)
Requires-Dist: leap.soledad.common (>=0.4.5)
Requires-Dist: leap.keymanager (>=0.3.4)
